hspsms/__init__.py
hspsms/backends.py
hspsms/main.py
hspsms-0.0.3.dist-info/LICENSE
hspsms-0.0.3.dist-info/METADATA
hspsms-0.0.3.dist-info/WHEEL
hspsms-0.0.3.dist-info/top_level.txt
hspsms-0.0.3.dist-info/RECORD
