Metadata-Version: 2.1
Name: hspsms
Version: 0.0.3
Summary: HSPSMS API Integration
Home-page: https://github.com/civilmachines/HSP-SMS-API
Author: 101Loop
Author-email: pypidev@civilmachines.com
License: GPLv3
Platform: UNKNOWN
Classifier: Development Status :: 5 - Production/Stable
Classifier: Environment :: Web Environment
Classifier: Intended Audience :: Developers
Classifier: License :: OSI Approved :: GNU General Public License v3 (GPLv3)
Classifier: Operating System :: OS Independent
Classifier: Programming Language :: Python
Classifier: Programming Language :: Python :: 3
Classifier: Programming Language :: Python :: 3.4
Classifier: Programming Language :: Python :: 3.5
Classifier: Programming Language :: Python :: 3.6
Classifier: Topic :: Internet :: WWW/HTTP
Requires-Python: !=2.*, !=3.0.*, !=3.1.*, !=3.2.*, !=3.3.*, >=3.4
Requires-Dist: certifi (>=2018.4.16)
Requires-Dist: chardet (>=3.0.4)
Requires-Dist: idna (>=2.7)
Requires-Dist: requests (>=2.19.1)
Requires-Dist: urllib3 (>=1.23)
